{
    "people": [
        {
        "name": "Mirsolikh MailRu",
        "email": "mirsamatmirsolih@mail.ru",
        "group": "admins"
        },
        {
        "name": "Mirsolikh Verifone",
        "email": "mirsolikhm1@verifone.com",
        "group": "admins"
        }, 
        {
        "name": "Mirsolikh Gmail",
        "email": "mirsamatmirsolih@gmail.com",
        "group": "developers"
        }, 
        {
        "name": "Mirsolikh Alex",
        "email": "alexclark2021@mail.ru",
        "group": "developers, admins"
        }  
    ],
    "licenses": [
        {
        "name": "Linux Anyconnect",
        "exp_date": "02.03.2022",
        "group": "admins",
        "script": "./scripts/01_linux.py"
        },
        {
        "name": "Microsoft Teams",
        "exp_date": "25.02.2022",
        "group": "admins",
        "script": "./scripts/01_linux.py"
        },
        {
        "name": "Microsoft",
        "exp_date": "02.03.2022",
        "group":"developers",
        "script": "./scripts/01_linux.py"
        },
        {
        "name": "Microsoft Office",
        "exp_date": "10.03.2022",
        "group": "developers",
        "script": "./scripts/01_linux.py"
        }
    ]
}